mm_dev_mcp/__init__.py
mm_dev_mcp/mm_dev_server_mock.py
mm_dev_mcp/server.py
ggoop_mm_dev_mcp-0.1.1.dist-info/METADATA
ggoop_mm_dev_mcp-0.1.1.dist-info/WHEEL
ggoop_mm_dev_mcp-0.1.1.dist-info/entry_points.txt
ggoop_mm_dev_mcp-0.1.1.dist-info/top_level.txt
ggoop_mm_dev_mcp-0.1.1.dist-info/RECORD
