Metadata-Version: 2.4
Name: ggoop-mm-dev-mcp
Version: 0.1.1
Summary: 制造云开发者平台
Requires-Python: >=3.13
Requires-Dist: fastapi[standard]>=0.115.13
Requires-Dist: fastmcp>=2.8.1
Requires-Dist: httpx>=0.28.1
Requires-Dist: mcp[cli]>=1.9.4
